karhu/Display_help.py
karhu/Errors.py
karhu/Recordaudio.py
karhu/SpeechToText.py
karhu/TextToSpeech.py
karhu/__init__.py
karhu/ai_assistant.py
karhu/animation.py
karhu/cli.py
karhu/config_parser.py
karhu/context_manager.py
karhu/document_processor.py
karhu/globals.py
karhu/interactive.py
karhu/kokorotts.py
karhu/model_manager.py
karhu/process_command.py
karhu/profile_manager.py
karhu/web_browser.py
karhu/config/models.json
karhu/config/profiles.json
karhu/config/system_prompt.json
karhu/data/.context
karhu/data/.karhu_history
karhu-2.0.0.dist-info/METADATA
karhu-2.0.0.dist-info/WHEEL
karhu-2.0.0.dist-info/entry_points.txt
karhu-2.0.0.dist-info/top_level.txt
karhu-2.0.0.dist-info/RECORD
