Metadata-Version: 2.4
Name: karhu
Version: 2.0.0
Summary: An AI assistant with PDF processing, web browsing, and speech capabilities
Author-email: Abderrahman Gaga <agaga@student.hive.fi>
License-Expression: Unlicense
Keywords: ai,assistant,chatbot,pdf,web,cli,speech-to-text,text-to-speech
Classifier: Development Status :: 4 - Beta
Classifier: Intended Audience :: Developers
Classifier: Intended Audience :: End Users/Desktop
Classifier: Programming Language :: Python :: 3
Classifier: Programming Language :: Python :: 3.8
Classifier: Programming Language :: Python :: 3.9
Classifier: Programming Language :: Python :: 3.10
Classifier: Programming Language :: Python :: 3.11
Classifier: Programming Language :: Python :: 3.12
Classifier: Programming Language :: Python :: 3.13
Classifier: Operating System :: OS Independent
Requires-Python: >=3.8
Requires-Dist: openai==1.72.0
Requires-Dist: requests==2.32.3
Requires-Dist: beautifulsoup4==4.13.3
Requires-Dist: html2text==2024.2.26
Requires-Dist: fake-useragent==2.1.0
Requires-Dist: pdfplumber==0.11.6
Requires-Dist: termcolor==3.0.1
Requires-Dist: rich==14.0.0
Requires-Dist: pyyaml==6.0.2
Requires-Dist: prompt_toolkit==3.0.50
Requires-Dist: google-cloud-texttospeech==2.25.1
Requires-Dist: google-cloud-speech==2.31.1
Requires-Dist: pyaudio==0.2.14
Requires-Dist: wave==0.0.2
Requires-Dist: pynput==1.8.1
